gias3.fieldwork-3.0.1-py3.11-nspkg.pth
gias3/fieldwork/__init__.py
gias3/fieldwork/field/__init__.py
gias3/fieldwork/field/ensemble_field_function.py
gias3/fieldwork/field/geometric_field.py
gias3/fieldwork/field/geometric_field_fitter.py
gias3/fieldwork/field/mapper.py
gias3/fieldwork/field/scalar_field.py
gias3/fieldwork/field/template_fields.py
gias3/fieldwork/field/template_fields_simplex_cubic.py
gias3/fieldwork/field/basis/__init__.py
gias3/fieldwork/field/basis/basis.py
gias3/fieldwork/field/field_ctypes/__init__.py
gias3/fieldwork/field/field_ctypes/ensemble_evaluators.py
gias3/fieldwork/field/tools/__init__.py
gias3/fieldwork/field/tools/curvature_tools.py
gias3/fieldwork/field/tools/discretisation.py
gias3/fieldwork/field/tools/fieldworkbin2json.py
gias3/fieldwork/field/tools/fitting_tools.py
gias3/fieldwork/field/tools/mesh_fitter.py
gias3/fieldwork/field/tools/misc.py
gias3/fieldwork/field/tools/spline_tools.py
gias3/fieldwork/field/tools/triangulate.py
gias3/fieldwork/field/topology/__init__.py
gias3/fieldwork/field/topology/element_types.py
gias3/fieldwork/field/topology/mesh.py
gias3/fieldwork/interactive/__init__.py
gias3/fieldwork/interactive/geometric_field_interactor.py
gias3/fieldwork/interactive/mesh_builder.py
gias3/fieldwork/interactive/point_picker_test.py
gias3.fieldwork-3.0.1.dist-info/LICENSE
gias3.fieldwork-3.0.1.dist-info/METADATA
gias3.fieldwork-3.0.1.dist-info/WHEEL
gias3.fieldwork-3.0.1.dist-info/namespace_packages.txt
gias3.fieldwork-3.0.1.dist-info/top_level.txt
gias3.fieldwork-3.0.1.dist-info/RECORD
